testqt/Aggregates.py
testqt/Aggregates.pyi
testqt/CoveredWarrantData.py
testqt/CoveredWarrantData.pyi
testqt/DerivativeData.py
testqt/DerivativeData.pyi
testqt/FiinIndicator.py
testqt/FiinIndicator.pyi
testqt/FiinSession.py
testqt/FiinSession.pyi
testqt/IndexData.py
testqt/IndexData.pyi
testqt/SubscribeCoveredWarrantEvents.py
testqt/SubscribeCoveredWarrantEvents.pyi
testqt/SubscribeDerivativeEvents.py
testqt/SubscribeDerivativeEvents.pyi
testqt/SubscribeIndexEvents.py
testqt/SubscribeIndexEvents.pyi
testqt/SubscribeTickerEvents.py
testqt/SubscribeTickerEvents.pyi
testqt/SubscribeTickerUpdate.py
testqt/SubscribeTickerUpdate.pyi
testqt/TickerData.py
testqt/TickerData.pyi
testqt/__init__.py
testqt/pyarmor_runtime_000000/pyarmor_runtime.pyd
testqt-0.0.0.10.dist-info/METADATA
testqt-0.0.0.10.dist-info/WHEEL
testqt-0.0.0.10.dist-info/top_level.txt
testqt-0.0.0.10.dist-info/RECORD
